metricz/__init__.py
metricz/cli.py
metricz/metricz.py
metricz-0.1.5.3.dist-info/DESCRIPTION.rst
metricz-0.1.5.3.dist-info/METADATA
metricz-0.1.5.3.dist-info/RECORD
metricz-0.1.5.3.dist-info/WHEEL
metricz-0.1.5.3.dist-info/entry_points.txt
metricz-0.1.5.3.dist-info/metadata.json
metricz-0.1.5.3.dist-info/top_level.txt
