Metadata-Version: 2.0
Name: metricz
Version: 0.1.5.3
Summary: Metricz makes it easy to write metrics to a Kairosdb instance running with OAuth2 security.
Home-page: https://github.com/jmcs/metricz
Author: João Santos
Author-email: jmcs@jsantos.eu
License: UNKNOWN
Keywords: metricz
Platform: UNKNOWN
Classifier: Development Status :: 2 - Pre-Alpha
Classifier: Intended Audience :: Developers
Classifier: Natural Language :: English
Classifier: Programming Language :: Python :: 2
Classifier: Programming Language :: Python :: 2.7
Classifier: Programming Language :: Python :: 3
Classifier: Programming Language :: Python :: 3.4
Classifier: Programming Language :: Python :: 3.5
Requires-Dist: requests
Requires-Dist: stups-tokens
Requires-Dist: click
Requires-Dist: clickclick
Requires-Dist: environmental (>=1.0)
